access_dict_by_dot/AccessDictByDot.py
access_dict_by_dot/__init__.py
access_dict_by_dot-0.0.3.dist-info/LICENSE.txt
access_dict_by_dot-0.0.3.dist-info/METADATA
access_dict_by_dot-0.0.3.dist-info/WHEEL
access_dict_by_dot-0.0.3.dist-info/top_level.txt
access_dict_by_dot-0.0.3.dist-info/RECORD
